CHANGELOG.md
LICENSE.txt
wagtail_sb_structblock/__init__.py
wagtail_sb_structblock/admin.py
wagtail_sb_structblock/apps.py
wagtail_sb_structblock/blocks/__init__.py
wagtail_sb_structblock/blocks/structblock.py
wagtail_sb_structblock/migrations/__init__.py
wagtail_sb_structblock/models.py
wagtail_sb_structblock/static/wagtail_sb_structblock/css/structblock.css
wagtail_sb_structblock/static/wagtail_sb_structblock/js/structblock.js
wagtail_sb_structblock/tests.py
wagtail_sb_structblock/version.py
wagtail_sb_structblock/views.py
wagtail_sb_structblock-0.2.0.dist-info/LICENSE.txt
wagtail_sb_structblock-0.2.0.dist-info/METADATA
wagtail_sb_structblock-0.2.0.dist-info/WHEEL
wagtail_sb_structblock-0.2.0.dist-info/RECORD
