Metadata-Version: 2.1
Name: wagtail-sb-structblock
Version: 0.2.0
Summary: Social Networks settings for wagtail sites.
Home-page: https://gitlab.com/softbutterfly/open-source/wagtail-sb-structblock
License: MIT
Keywords: Softbutterfly,Django,Migrations
Author: SoftButterfly Development Team
Author-email: dev@softbutterfly.io
Requires-Python: >=3.8.1,<4.0.0
Classifier: Development Status :: 4 - Beta
Classifier: Environment :: Web Environment
Classifier: Framework :: Django :: 2
Classifier: Framework :: Django :: 3
Classifier: Framework :: Django :: 4
Classifier: Framework :: Wagtail :: 3
Classifier: Framework :: Wagtail :: 4
Classifier: Framework :: Wagtail :: 5
Classifier: Intended Audience :: Developers
Classifier: License :: OSI Approved :: MIT License
Classifier: Natural Language :: English
Classifier: Programming Language :: Python :: 3
Classifier: Programming Language :: Python :: 3.9
Classifier: Programming Language :: Python :: 3.10
Classifier: Programming Language :: Python :: 3.11
Classifier: Programming Language :: Python :: 3.8
Classifier: Topic :: Software Development :: Libraries :: Python Modules
Requires-Dist: Django (<5.0)
Requires-Dist: djangorestframework (<4.0)
Requires-Dist: wagtail (<6.0)
Project-URL: Bug Tracker, https://gitlab.com/softbutterfly/open-source/wagtail-sb-structblock/-/issues
Project-URL: Documentation, https://gitlab.com/softbutterfly/open-source/wagtail-sb-structblock/-/wikis
Project-URL: Download, https://gitlab.com/softbutterfly/open-source/wagtail-sb-structblock/-/archive/v0.2.0/wagtail-sb-structblock-v0.2.0.tar.gz
Project-URL: Repository, https://gitlab.com/softbutterfly/open-source/wagtail-sb-structblock
